README.rst
setup.py
mmdminterface/HTMLTestRunner.py
mmdminterface/__init__.py
mmdminterface/auto_test_api.py
mmdminterface/ddt.py
mmdminterface/read_test_data.py
mmdminterface/test_api.py
mmdminterface.egg-info/PKG-INFO
mmdminterface.egg-info/SOURCES.txt
mmdminterface.egg-info/dependency_links.txt
mmdminterface.egg-info/requires.txt
mmdminterface.egg-info/top_level.txt