Metadata-Version: 1.1
Name: mmdminterface
Version: 0.2
Summary: mmdminterface
Home-page: https://github.com/mckay58/minterface
Author: KingMckay
Author-email: kingmckay58@gmail.mmdminterface
License: MIT
Platform: UNKNOWN
Classifier: Development Status :: 3 - Alpha
Classifier: Intended Audience :: Developers
Classifier: Topic :: Software Development :: Build Tools
Classifier: License :: OSI Approved :: MIT License
Classifier: Programming Language :: Python :: 3.5
Classifier: Programming Language :: Python :: 3.6
